kwmatrix/__init__.py
kwmatrix/kwmatrix.py
kwmatrix-1.0.1.dist-info/LICENSE
kwmatrix-1.0.1.dist-info/METADATA
kwmatrix-1.0.1.dist-info/WHEEL
kwmatrix-1.0.1.dist-info/top_level.txt
kwmatrix-1.0.1.dist-info/RECORD
