Metadata-Version: 2.1
Name: kwmatrix
Version: 1.0.1
Summary: Combine keywords with several modifiers for SEO
Home-page: https://github.com/joejoinerr/kwmatrix
Author: Joe Joiner
Author-email: joe@legato.digital
License: GPL
Platform: UNKNOWN
